mysqld_integration_test/__init__.py
mysqld_integration_test/attributes.py
mysqld_integration_test/exceptions.py
mysqld_integration_test/helpers.py
mysqld_integration_test/log.py
mysqld_integration_test/mysqld.py
mysqld_integration_test/settings.py
mysqld_integration_test/version.py
mysqld_integration_test-0.0.28.dist-info/LICENSE
mysqld_integration_test-0.0.28.dist-info/METADATA
mysqld_integration_test-0.0.28.dist-info/WHEEL
mysqld_integration_test-0.0.28.dist-info/top_level.txt
mysqld_integration_test-0.0.28.dist-info/RECORD
